{
    "header": {
        "generatorPublicKey": "",
        "height": 0,
        "previousBlockID": "",
        "reward": "0",
        "signature": "",
        "timestamp": 1651529526,
        "transactionRoot": "e3b0c44298fc1c149afbf4c8996fb92427ae41e4649b934ca495991b7852b855",
        "version": 0,
        "asset": {
            "initRounds": 3,
            "initDelegates": [
                "23404404f2c8d8647f6a554a368088f2325bf8ba",
                "4398b600b01b7e219ec1eb7bd82f0b18d587986f",
                "5d0d01086f558f144d562e4829fa1307b6a19fd9",
                "bd63d8595ae5947c927fe2fdb797ea5e7fcdeb67",
                "de7681929cfb650e761543aef8bffc5734c3d922"
            ],
            "accounts": [
                {
                    "token": {
                        "balance": "25000000000"
                    },
                    "dpos": {
                        "delegate": {
                            "username": "",
                            "pomHeights": [],
                            "consecutiveMissedBlocks": 0,
                            "lastForgedHeight": 0,
                            "isBanned": false,
                            "totalVotesReceived": "0"
                        },
                        "sentVotes": [],
                        "unlocking": []
                    },
                    "keys": {
                        "mandatoryKeys": [],
                        "optionalKeys": [],
                        "numberOfSignatures": 0
                    },
                    "sequence": {
                        "nonce": "0"
                    },
                    "naive": {
                        "trustFacts": "TrF: "
                    },
                    "address": "10341b80ecb29d718d991926d66c269810f4b630"
                },
                {
                    "token": {
                        "balance": "100000000"
                    },
                    "dpos": {
                        "delegate": {
                            "username": "genesisDelegate1",
                            "pomHeights": [],
                            "consecutiveMissedBlocks": 0,
                            "lastForgedHeight": 0,
                            "isBanned": false,
                            "totalVotesReceived": "0"
                        },
                        "sentVotes": [],
                        "unlocking": []
                    },
                    "keys": {
                        "mandatoryKeys": [],
                        "optionalKeys": [],
                        "numberOfSignatures": 0
                    },
                    "sequence": {
                        "nonce": "0"
                    },
                    "naive": {
                        "trustFacts": "TrF: "
                    },
                    "address": "23404404f2c8d8647f6a554a368088f2325bf8ba"
                },
                {
                    "token": {
                        "balance": "100000000"
                    },
                    "dpos": {
                        "delegate": {
                            "username": "genesisDelegate4",
                            "pomHeights": [],
                            "consecutiveMissedBlocks": 0,
                            "lastForgedHeight": 0,
                            "isBanned": false,
                            "totalVotesReceived": "0"
                        },
                        "sentVotes": [],
                        "unlocking": []
                    },
                    "keys": {
                        "mandatoryKeys": [],
                        "optionalKeys": [],
                        "numberOfSignatures": 0
                    },
                    "sequence": {
                        "nonce": "0"
                    },
                    "naive": {
                        "trustFacts": "TrF: "
                    },
                    "address": "4398b600b01b7e219ec1eb7bd82f0b18d587986f"
                },
                {
                    "token": {
                        "balance": "25000000000"
                    },
                    "dpos": {
                        "delegate": {
                            "username": "",
                            "pomHeights": [],
                            "consecutiveMissedBlocks": 0,
                            "lastForgedHeight": 0,
                            "isBanned": false,
                            "totalVotesReceived": "0"
                        },
                        "sentVotes": [],
                        "unlocking": []
                    },
                    "keys": {
                        "mandatoryKeys": [],
                        "optionalKeys": [],
                        "numberOfSignatures": 0
                    },
                    "sequence": {
                        "nonce": "0"
                    },
                    "naive": {
                        "trustFacts": "TrF: "
                    },
                    "address": "5b213d3bfea568cda423077a5d2092c6defe201c"
                },
                {
                    "token": {
                        "balance": "100000000"
                    },
                    "dpos": {
                        "delegate": {
                            "username": "genesisDelegate2",
                            "pomHeights": [],
                            "consecutiveMissedBlocks": 0,
                            "lastForgedHeight": 0,
                            "isBanned": false,
                            "totalVotesReceived": "0"
                        },
                        "sentVotes": [],
                        "unlocking": []
                    },
                    "keys": {
                        "mandatoryKeys": [],
                        "optionalKeys": [],
                        "numberOfSignatures": 0
                    },
                    "sequence": {
                        "nonce": "0"
                    },
                    "naive": {
                        "trustFacts": "TrF: "
                    },
                    "address": "5d0d01086f558f144d562e4829fa1307b6a19fd9"
                },
                {
                    "token": {
                        "balance": "25000000000"
                    },
                    "dpos": {
                        "delegate": {
                            "username": "",
                            "pomHeights": [],
                            "consecutiveMissedBlocks": 0,
                            "lastForgedHeight": 0,
                            "isBanned": false,
                            "totalVotesReceived": "0"
                        },
                        "sentVotes": [],
                        "unlocking": []
                    },
                    "keys": {
                        "mandatoryKeys": [],
                        "optionalKeys": [],
                        "numberOfSignatures": 0
                    },
                    "sequence": {
                        "nonce": "0"
                    },
                    "naive": {
                        "trustFacts": "TrF: "
                    },
                    "address": "69240d34d049283d893118eeb7a910915f1e9f10"
                },
                {
                    "token": {
                        "balance": "100000000"
                    },
                    "dpos": {
                        "delegate": {
                            "username": "genesisDelegate5",
                            "pomHeights": [],
                            "consecutiveMissedBlocks": 0,
                            "lastForgedHeight": 0,
                            "isBanned": false,
                            "totalVotesReceived": "0"
                        },
                        "sentVotes": [],
                        "unlocking": []
                    },
                    "keys": {
                        "mandatoryKeys": [],
                        "optionalKeys": [],
                        "numberOfSignatures": 0
                    },
                    "sequence": {
                        "nonce": "0"
                    },
                    "naive": {
                        "trustFacts": "TrF: "
                    },
                    "address": "bd63d8595ae5947c927fe2fdb797ea5e7fcdeb67"
                },
                {
                    "token": {
                        "balance": "100000000"
                    },
                    "dpos": {
                        "delegate": {
                            "username": "genesisDelegate3",
                            "pomHeights": [],
                            "consecutiveMissedBlocks": 0,
                            "lastForgedHeight": 0,
                            "isBanned": false,
                            "totalVotesReceived": "0"
                        },
                        "sentVotes": [],
                        "unlocking": []
                    },
                    "keys": {
                        "mandatoryKeys": [],
                        "optionalKeys": [],
                        "numberOfSignatures": 0
                    },
                    "sequence": {
                        "nonce": "0"
                    },
                    "naive": {
                        "trustFacts": "TrF: "
                    },
                    "address": "de7681929cfb650e761543aef8bffc5734c3d922"
                }
            ]
        },
        "id": "103bfd05839661ac7257182144fce58cdb63f9ea380d62e81ec859850d6f441d"
    },
    "payload": []
}